MANIFEST.in
README.rst
setup.py
collective/__init__.py
collective.mass_subscriptions.egg-info/PKG-INFO
collective.mass_subscriptions.egg-info/SOURCES.txt
collective.mass_subscriptions.egg-info/dependency_links.txt
collective.mass_subscriptions.egg-info/entry_points.txt
collective.mass_subscriptions.egg-info/namespace_packages.txt
collective.mass_subscriptions.egg-info/not-zip-safe
collective.mass_subscriptions.egg-info/requires.txt
collective.mass_subscriptions.egg-info/top_level.txt
collective/mass_subscriptions/__init__.py
collective/mass_subscriptions/configure.zcml
collective/mass_subscriptions/Extensions/install.py
collective/mass_subscriptions/browser/__init__.py
collective/mass_subscriptions/browser/configure.zcml
collective/mass_subscriptions/browser/mass_subscriptions.pt
collective/mass_subscriptions/browser/subscriptions.py
collective/mass_subscriptions/locales/collective.mass_subscriptions.pot
collective/mass_subscriptions/locales/runi18ndude.sh
collective/mass_subscriptions/locales/it/LC_MESSAGES/collective.mass_subscriptions.mo
collective/mass_subscriptions/locales/it/LC_MESSAGES/collective.mass_subscriptions.po
collective/mass_subscriptions/profiles/default/controlpanel.xml
collective/mass_subscriptions/profiles/default/metadata.xml
collective/mass_subscriptions/profiles/uninstall/controlpanel.xml
docs/HISTORY.txt
docs/INSTALL.txt
docs/LICENSE.GPL
docs/LICENSE.txt