Metadata-Version: 1.1
Name: collective.mass-subscriptions
Version: 0.1.1
Summary: Give to Plone administrators a form where is possible to subscribe multiple users in a single operation
Home-page: http://plone.org/products/collective.mass_subscriptions
Author: RedTurtle Technology
Author-email: sviluppoplone@redturtle.it
License: GPL
Keywords: plone users plonegov subscription
Platform: UNKNOWN
Classifier: Framework :: Plone
Classifier: Development Status :: 4 - Beta
Classifier: Framework :: Plone :: 3.3
Classifier: Framework :: Plone :: 4.0
Classifier: Framework :: Plone :: 4.1
Classifier: Programming Language :: Python
